[{"line":2,"elements":[{"line":4,"name":"","description":"","type":"background","keyword":"Background","steps":[{"result":{"duration":4964087800,"status":"passed"},"line":5,"name":"fixture is loaded","match":{"location":"com.stepDefinitionTestNG.LoginSteps.fixture_is_loaded()"},"keyword":"Given "},{"result":{"duration":128654400,"status":"passed"},"line":6,"name":"user navigate to login page","match":{"location":"com.stepDefinitionTestNG.LoginSteps.user_navigate_to_login_page()"},"keyword":"When "},{"result":{"duration":238379500,"status":"passed"},"line":7,"name":"enter username in username field","match":{"location":"com.stepDefinitionTestNG.LoginSteps.enter_username_in_username_field()"},"keyword":"When "},{"result":{"duration":210435600,"status":"passed"},"line":8,"name":"enter password in password field","match":{"location":"com.stepDefinitionTestNG.LoginSteps.enter_password_in_password_field()"},"keyword":"When "},{"result":{"duration":1837578500,"status":"passed"},"line":9,"name":"Click on Login button","match":{"location":"com.stepDefinitionTestNG.LoginSteps.click_on_login_button()"},"keyword":"When "},{"result":{"duration":5188008900,"status":"passed"},"line":10,"name":"Dashboard page should be displayed","match":{"location":"com.stepDefinitionTestNG.LoginSteps.dashboard_page_should_be_displayed()"},"keyword":"Then "}]},{"start_timestamp":"2025-11-20T12:02:31.915Z","before":[{"result":{"duration":2992100,"status":"passed"},"match":{"location":"com.hooks.AppHooks.getScenarioTag(io.cucumber.java.Scenario)"}},{"result":{"duration":15937244900,"status":"passed"},"match":{"location":"com.hooks.AppHooks.init()"}}],"line":13,"name":"When user click on menu items the all submenu items should be displayed","description":"","id":"verify-all-menu-items;when-user-click-on-menu-items-the-all-submenu-items-should-be-displayed","after":[{"result":{"duration":6027734800,"status":"passed"},"match":{"location":"com.hooks.AppHooks.tearDown(io.cucumber.java.Scenario)"}}],"type":"scenario","keyword":"Scenario","steps":[{"result":{"duration":35206618400,"status":"passed"},"line":15,"name":"user navigate to Admin page","match":{"location":"com.stepDefinitionTestNG.Steps.user_navigate_to_admin_page()"},"keyword":"Given "},{"result":{"duration":276589000,"status":"passed"},"line":16,"name":"all below menu items gets displayed","match":{"location":"com.stepDefinitionTestNG.Steps.all_below_menu_items_gets_displayed(io.cucumber.datatable.DataTable)"},"rows":[{"cells":["User Management"]},{"cells":["Job"]},{"cells":["Organization"]},{"cells":["Qualifications"]},{"cells":["Nationalities"]},{"cells":["Corporate Branding"]},{"cells":["Configuration"]}],"keyword":"Then "},{"result":{"duration":13235122100,"status":"passed"},"line":24,"name":"user click on User Management","match":{"location":"com.stepDefinitionTestNG.Steps.user_click_on_user_management()"},"keyword":"When "},{"result":{"duration":11146645000,"status":"passed"},"line":25,"name":"Users should be displayed","match":{"location":"com.stepDefinitionTestNG.Steps.users_should_be_displayed()"},"keyword":"Then "},{"result":{"duration":23604926200,"status":"passed"},"line":26,"name":"user click on Job","match":{"location":"com.stepDefinitionTestNG.Steps.user_click_on_job()"},"keyword":"And "},{"result":{"duration":331996900,"status":"passed"},"line":27,"name":"all below sub menu items gets displayed","match":{"location":"com.stepDefinitionTestNG.Steps.all_below_sub_menu_items_gets_displayed(io.cucumber.datatable.DataTable)"},"rows":[{"cells":["Job Titles"]},{"cells":["Pay Grades"]},{"cells":["Employment Status"]},{"cells":["Job Categories"]},{"cells":["Work Shifts"]}],"keyword":"Then "}],"tags":[{"name":"@TC002"}]}],"name":"Verify all menu items","description":"","id":"verify-all-menu-items","keyword":"Feature","uri":"file:src/test/resources/features/menuitems.feature","tags":[]}]